src/__init__.py
src/__main__.py
gen_pptx_from_simple_text-2.0.0.dist-info/LICENSE
gen_pptx_from_simple_text-2.0.0.dist-info/METADATA
gen_pptx_from_simple_text-2.0.0.dist-info/WHEEL
gen_pptx_from_simple_text-2.0.0.dist-info/entry_points.txt
gen_pptx_from_simple_text-2.0.0.dist-info/top_level.txt
gen_pptx_from_simple_text-2.0.0.dist-info/RECORD
