Metadata-Version: 2.1
Name: gen-pptx-from-simple-text
Version: 2.0.0
Summary: CLI to generate powerpoint slides from simple text file[s].
Home-page: https://github.com/sukujgrg/gen-pptx-from-simple-text
Author: Suku John George
Author-email: sukujgrg@gmail.com
License: MIT
Platform: UNKNOWN
Classifier: Programming Language :: Python :: 3
Classifier: Operating System :: OS Independent
Requires-Python: >=3.4
Requires-Dist: click (==7.*)
Requires-Dist: python-pptx (==0.6.*)
